dnnmodels/__init__.py
dnnmodels/conv2d.py
dnnmodels/flatten.py
dnnmodels/fully_connected.py
dnnmodels/get_model.py
dnnmodels/layer.py
dnnmodels/lrn.py
dnnmodels/max_pool.py
dnnmodels/mlp.py
dnnmodels/relu.py
dnnmodels/softmax.py
dnnmodels/train_graph.py
dnnmodels/utils.py
dnnmodels-1.0.0.dist-info/METADATA
dnnmodels-1.0.0.dist-info/RECORD
dnnmodels-1.0.0.dist-info/WHEEL
dnnmodels-1.0.0.dist-info/top_level.txt
lib/__init__.py
lib/conv2d.py
lib/flatten.py
lib/fully_connected.py
lib/get_model.py
lib/layer.py
lib/lrn.py
lib/max_pool.py
lib/mlp.py
lib/relu.py
lib/softmax.py
lib/train_graph.py
lib/utils.py
