Metadata-Version: 2.1
Name: dnnmodels
Version: 1.0.0
Summary: Simple models inspired by Cleverhans that help create DNN Architectures
Home-page: https://github.com/NullConvergence/dnnmodels
Author: NullConvergence
Author-email: UNKNOWN
License: MIT
Platform: UNKNOWN
Requires-Dist: cleverhans
Requires-Dist: tensorflow
